{
    "title": "KLAX",
    "platform": "Game Boy Color",
    "sgb_support": "",
    "publisher": "Midway",
    "publisher_code": "5D",
    "cartridge_type": "ROM+MBC5",
    "cartridge_type_code": "19",
    "rom_size": "1MB",
    "rom_size_code": "05",
    "ram_size": "0KB",
    "ram_size_code": "00",
    "destination": "",
    "version": "00",
    "header_checksum": "6C",
    "global_checksum": "172E",
    "fullName": "Klax (USA, Europe)",
    "coverImage": "/covers/Klax (USA, Europe).png",
    "publisher_cart": "Midway",
    "releaseDate": "Unknown Date",
    "releaseMonth": "Unknown Month",
    "genre": "Strategy",
    "crc": "7181CBD0",
    "cartSize": 1048576,
    "checksum1000": "B0F4",
    "checksumFull": "2941773"
}