{
    "title": "BEAR IN THEBBNP",
    "platform": "Game Boy Color",
    "sgb_support": "",
    "publisher": "Ubisoft",
    "publisher_code": "41",
    "cartridge_type": "ROM+MBC5",
    "cartridge_type_code": "19",
    "rom_size": "1MB",
    "rom_size_code": "05",
    "ram_size": "0KB",
    "ram_size_code": "00",
    "destination": "",
    "version": "00",
    "header_checksum": "7C",
    "global_checksum": "186B",
    "fullName": "Jim Henson's Bear in the Big Blue House (Europe) (En,Fr,De,Es,It,Nl)",
    "coverImage": "/covers/Jim Henson's Bear in the Big Blue House (Europe) (En,Fr,De,Es,It,Nl).png",
    "publisher_cart": "Ubi Soft Entertainment",
    "releaseDate": "Unknown Date",
    "releaseMonth": "Unknown Month",
    "genre": "Educational",
    "crc": "48C99939",
    "cartSize": 1048576,
    "checksum1000": "B11E",
    "checksumFull": "23618EE"
}