{
    "title": "KLAX",
    "platform": "Game Boy",
    "sgb_support": "",
    "publisher": "Hudson",
    "publisher_code": "18",
    "cartridge_type": "ROM",
    "cartridge_type_code": "00",
    "rom_size": "32KB",
    "rom_size_code": "00",
    "ram_size": "0KB",
    "ram_size_code": "00",
    "destination": "Japan",
    "version": "00",
    "header_checksum": "9F",
    "global_checksum": "27BC",
    "fullName": "Klax (Japan) (Hudson Soft)",
    "coverImage": "/covers/Klax (Japan) (Hudson Soft).png",
    "publisher_cart": "Hudson Soft Japan",
    "releaseDate": "1990",
    "releaseMonth": "12",
    "genre": "Puzzle-Game",
    "crc": "B4955889",
    "cartSize": 32768,
    "checksum1000": "FD6",
    "checksumFull": "39289F"
}