{
    "title": "DONKEYKONGLAND 3",
    "platform": "Super Game Boy",
    "sgb_support": "yes",
    "publisher": "Nintendo",
    "publisher_code": "01",
    "cartridge_type": "ROM+MBC1+RAM+BATT",
    "cartridge_type_code": "03",
    "rom_size": "512KB",
    "rom_size_code": "04",
    "ram_size": "8KB",
    "ram_size_code": "02",
    "destination": "",
    "version": "01",
    "header_checksum": "DA",
    "global_checksum": "3B41",
    "fullName": "Donkey Kong Land III (USA, Europe) (Rev 1) (SGB Enhanced)",
    "coverImage": "/covers/Donkey Kong Land III (USA, Europe) (Rev 1) (SGB Enhanced).png",
    "publisher_cart": "Nintendo",
    "releaseDate": "Unknown Date",
    "releaseMonth": "Unknown Month",
    "genre": "Platform",
    "crc": "A19ACDB6",
    "cartSize": 524288,
    "checksum1000": "CC5A",
    "checksumFull": "32B3BBD"
}