{
    "title": "HARRY POTTER 3",
    "platform": "Game Boy Color",
    "sgb_support": "",
    "publisher": "Unknown Publisher",
    "publisher_code": "MK",
    "cartridge_type": "ROM+MBC5+RAM+BATT",
    "cartridge_type_code": "1B",
    "rom_size": "1MB",
    "rom_size_code": "05",
    "ram_size": "8KB",
    "ram_size_code": "02",
    "destination": "Japan",
    "version": "00",
    "header_checksum": "A3",
    "global_checksum": "4517",
    "fullName": "Harry Potter 3 (USA) (Unl)",
    "coverImage": null,
    "publisher_cart": "",
    "releaseDate": "Unknown Date",
    "releaseMonth": "Unknown Month",
    "genre": "Unknown Genre",
    "crc": "D0FECE32",
    "cartSize": 1048576,
    "checksum1000": "27FF8",
    "checksumFull": "A014573"
}