{
    "title": "MANSELL",
    "platform": "Game Boy",
    "sgb_support": "",
    "publisher": "GameTek",
    "publisher_code": "54",
    "cartridge_type": "ROM+MBC1",
    "cartridge_type_code": "01",
    "rom_size": "128KB",
    "rom_size_code": "02",
    "ram_size": "0KB",
    "ram_size_code": "00",
    "destination": "",
    "version": "00",
    "header_checksum": "83",
    "global_checksum": "56D5",
    "fullName": "Nigel Mansell's World Championship Racing (USA)",
    "coverImage": "/covers/Nigel Mansell's World Championship Racing (USA).png",
    "publisher_cart": "Take 2 Interactive",
    "releaseDate": "1993",
    "releaseMonth": "8",
    "genre": "Race, Driving",
    "crc": "03E84D7D",
    "cartSize": 131072,
    "checksum1000": "3334",
    "checksumFull": "BD5800"
}