{
    "title": "BOKUMONOGB BYWJ",
    "platform": "Super Game Boy",
    "sgb_support": "yes",
    "publisher": "Natsume",
    "publisher_code": "99",
    "cartridge_type": "ROM+MBC3+RAM+BATT",
    "cartridge_type_code": "13",
    "rom_size": "512KB",
    "rom_size_code": "04",
    "ram_size": "8KB",
    "ram_size_code": "02",
    "destination": "Japan",
    "version": "00",
    "header_checksum": "D7",
    "global_checksum": "6C36",
    "fullName": "Bokujou Monogatari GB (Japan) (SGB Enhanced) (NP)",
    "coverImage": "/covers/Bokujou Monogatari GB (Japan) (SGB Enhanced) (NP).png",
    "publisher_cart": "Victor Interactive Software",
    "releaseDate": "1997",
    "releaseMonth": "12",
    "genre": "Simulation",
    "crc": "0424DF85",
    "cartSize": 524288,
    "checksum1000": "D797",
    "checksumFull": "3516CD8"
}