{
    "title": "CHILDSOCCERBJFJ",
    "platform": "Game Boy Color",
    "sgb_support": "",
    "publisher": "Success",
    "publisher_code": "8N",
    "cartridge_type": "ROM+MBC5+RAM+BATT",
    "cartridge_type_code": "1B",
    "rom_size": "2MB",
    "rom_size_code": "06",
    "ram_size": "32KB",
    "ram_size_code": "03",
    "destination": "Japan",
    "version": "00",
    "header_checksum": "0B",
    "global_checksum": "D39C",
    "fullName": "Zen-Nihon Shounen Soccer Taikai - Mezase Nihon Ichi! (Japan)",
    "coverImage": "/covers/Zen-Nihon Shounen Soccer Taikai - Mezase Nihon Ichi! (Japan).png",
    "publisher_cart": "Success",
    "releaseDate": "2001",
    "releaseMonth": "9",
    "genre": "Sports",
    "crc": "EFAD8B34",
    "cartSize": 2097152,
    "checksum1000": "252C6",
    "checksumFull": "972D50B"
}