{
    "title": "Dennis",
    "platform": "Game Boy",
    "sgb_support": "",
    "publisher": "Ocean",
    "publisher_code": "67",
    "cartridge_type": "ROM+MBC1",
    "cartridge_type_code": "01",
    "rom_size": "128KB",
    "rom_size_code": "02",
    "ram_size": "0KB",
    "ram_size_code": "00",
    "destination": "",
    "version": "10",
    "header_checksum": "0B",
    "global_checksum": "12AA",
    "fullName": "Dennis (Europe) (Beta) (1993-09-13)",
    "coverImage": null,
    "publisher_cart": "Ocean",
    "releaseDate": "Unknown Date",
    "releaseMonth": "Unknown Month",
    "genre": "Platform",
    "crc": "807D34A4",
    "cartSize": 131072,
    "checksum1000": "2FDF",
    "checksumFull": "C21366"
}