{
    "title": "F1 WORLD GPAFIJ",
    "platform": "Game Boy Color",
    "sgb_support": "",
    "publisher": "Video System",
    "publisher_code": "01",
    "cartridge_type": "ROM+MBC5+RAM+BATT",
    "cartridge_type_code": "1B",
    "rom_size": "1MB",
    "rom_size_code": "05",
    "ram_size": "8KB",
    "ram_size_code": "02",
    "destination": "Japan",
    "version": "00",
    "header_checksum": "81",
    "global_checksum": "551E",
    "fullName": "F-1 World Grand Prix (Japan) (En) (Beta 2)",
    "coverImage": null,
    "publisher_cart": "Nintendo",
    "releaseDate": "Unknown Date",
    "releaseMonth": "Unknown Month",
    "genre": "Race, Driving",
    "crc": "5E24811E",
    "cartSize": 1048576,
    "checksum1000": "15DCE",
    "checksumFull": "58F5591"
}