{
    "title": "BEYBLADE2  BBVJ",
    "platform": "Game Boy Color",
    "sgb_support": "",
    "publisher": "Hudson",
    "publisher_code": "18",
    "cartridge_type": "ROM+MBC5+RAM+BATT",
    "cartridge_type_code": "1B",
    "rom_size": "2MB",
    "rom_size_code": "06",
    "ram_size": "32KB",
    "ram_size_code": "03",
    "destination": "Japan",
    "version": "00",
    "header_checksum": "D9",
    "global_checksum": "F4B5",
    "fullName": "Beyblade - Fighting Tournament (Japan)",
    "coverImage": "/covers/Beyblade - Fighting Tournament (Japan).png",
    "publisher_cart": "Hudson Soft Japan",
    "releaseDate": "2000",
    "releaseMonth": "8",
    "genre": "Unknown Genre",
    "crc": "1EC9DB95",
    "cartSize": 2097152,
    "checksum1000": "37400",
    "checksumFull": "DDAF65E"
}