{
    "title": "DESSERT    B3DJ",
    "platform": "Game Boy Color",
    "sgb_support": "",
    "publisher": "MTO Co",
    "publisher_code": "BL",
    "cartridge_type": "ROM+MBC5+RAM+BATT",
    "cartridge_type_code": "1B",
    "rom_size": "1MB",
    "rom_size_code": "05",
    "ram_size": "8KB",
    "ram_size_code": "02",
    "destination": "Japan",
    "version": "00",
    "header_checksum": "27",
    "global_checksum": "FC59",
    "fullName": "Nakayoshi Cooking Series 4 - Tanoshii Dessert (Japan)",
    "coverImage": "/covers/Nakayoshi Cooking Series 4 - Tanoshii Dessert (Japan).png",
    "publisher_cart": "MTO Inc.",
    "releaseDate": "2001",
    "releaseMonth": "11",
    "genre": "Unknown Genre",
    "crc": "7E5C8542",
    "cartSize": 1048576,
    "checksum1000": "18E9C",
    "checksumFull": "635FDAE"
}