{
    "title": "H-MOON2 CGBBM2E",
    "platform": "Game Boy Color",
    "sgb_support": "yes",
    "publisher": "Natsume",
    "publisher_code": "E9",
    "cartridge_type": "ROM+MBC5+RAM+BATT",
    "cartridge_type_code": "1B",
    "rom_size": "2MB",
    "rom_size_code": "06",
    "ram_size": "32KB",
    "ram_size_code": "03",
    "destination": "",
    "version": "00",
    "header_checksum": "BC",
    "global_checksum": "271C",
    "fullName": "Harvest Moon 2 GBC (USA) (SGB Enhanced) (GB Compatible)",
    "coverImage": "/covers/Harvest Moon 2 GBC (USA) (SGB Enhanced) (GB Compatible).png",
    "publisher_cart": "Natsume",
    "releaseDate": "2000",
    "releaseMonth": "11",
    "genre": "Strategy",
    "crc": "08906220",
    "cartSize": 2097152,
    "checksum1000": "6422D",
    "checksumFull": "1843275F"
}