{
    "title": "IDE-GB     BIMJ",
    "platform": "Game Boy Color",
    "sgb_support": "",
    "publisher": "Athena",
    "publisher_code": "E7",
    "cartridge_type": "ROM+MBC5+RAM+BATT",
    "cartridge_type_code": "1B",
    "rom_size": "2MB",
    "rom_size_code": "06",
    "ram_size": "8KB",
    "ram_size_code": "02",
    "destination": "Japan",
    "version": "00",
    "header_checksum": "AB",
    "global_checksum": "F819",
    "fullName": "Ide Yousuke no Mahjong Kyoushitsu GB (Japan)",
    "coverImage": "/covers/Ide Yousuke no Mahjong Kyoushitsu GB (Japan).png",
    "publisher_cart": "Athena",
    "releaseDate": "2000",
    "releaseMonth": "6",
    "genre": "Asiatic board game",
    "crc": "61DF88CA",
    "cartSize": 2097152,
    "checksum1000": "23DE3",
    "checksumFull": "8E3F92A"
}