{
    "title": "PAWA POKE2 BPWJ",
    "platform": "Game Boy Color",
    "sgb_support": "yes",
    "publisher": "Konami",
    "publisher_code": "A4",
    "cartridge_type": "ROM+MBC5+RAM+BATT",
    "cartridge_type_code": "1B",
    "rom_size": "2MB",
    "rom_size_code": "06",
    "ram_size": "32KB",
    "ram_size_code": "03",
    "destination": "Japan",
    "version": "00",
    "header_checksum": "BB",
    "global_checksum": "A977",
    "fullName": "Power Pro Kun Pocket 2 (Japan) (SGB Enhanced) (GB Compatible)",
    "coverImage": "/covers/Power Pro Kun Pocket 2 (Japan) (SGB Enhanced) (GB Compatible).png",
    "publisher_cart": "Konami",
    "releaseDate": "2000",
    "releaseMonth": "3",
    "genre": "Sports",
    "crc": "C2A4A3EB",
    "cartSize": 2097152,
    "checksum1000": "32F32",
    "checksumFull": "C16AA97"
}