{
    "title": "POCKETCAMERA",
    "platform": "Super Game Boy",
    "sgb_support": "yes",
    "publisher": "Unknown Publisher",
    "publisher_code": "01",
    "cartridge_type": "ROM+POCKET CAMERA",
    "cartridge_type_code": "FC",
    "rom_size": "1MB",
    "rom_size_code": "05",
    "ram_size": "128KB",
    "ram_size_code": "04",
    "destination": "Japan",
    "version": "01",
    "header_checksum": "DB",
    "global_checksum": "9362",
    "fullName": "Pocket Camera (Japan) (Rev 1) (SGB Enhanced)",
    "coverImage": "/covers/Pocket Camera (Japan) (Rev 1) (SGB Enhanced).png",
    "publisher_cart": "Nintendo",
    "releaseDate": "Unknown Date",
    "releaseMonth": "Unknown Month",
    "genre": "Action",
    "crc": "73E8EF96",
    "cartSize": 1048576,
    "checksum1000": "1B839",
    "checksumFull": "6359457"
}