{
    "title": "QUIQUI",
    "platform": "Game Boy Color",
    "sgb_support": "",
    "publisher": "Magical Company",
    "publisher_code": "BG",
    "cartridge_type": "ROM+MBC5+RAM+BATT",
    "cartridge_type_code": "1B",
    "rom_size": "1MB",
    "rom_size_code": "05",
    "ram_size": "8KB",
    "ram_size_code": "02",
    "destination": "Japan",
    "version": "00",
    "header_checksum": "AB",
    "global_checksum": "8748",
    "fullName": "Qui Qui (Japan) (GB Compatible)",
    "coverImage": "/covers/Qui Qui (Japan) (GB Compatible).png",
    "publisher_cart": "Magical",
    "releaseDate": "1999",
    "releaseMonth": "3",
    "genre": "Strategy",
    "crc": "56D76BA2",
    "cartSize": 1048576,
    "checksum1000": "15F0C",
    "checksumFull": "53E8817"
}