{
    "title": "ROCK'N! MONSTER!",
    "platform": "Super Game Boy",
    "sgb_support": "yes",
    "publisher": "Hori",
    "publisher_code": "A1",
    "cartridge_type": "ROM+MBC1",
    "cartridge_type_code": "01",
    "rom_size": "512KB",
    "rom_size_code": "04",
    "ram_size": "0KB",
    "ram_size_code": "00",
    "destination": "Japan",
    "version": "00",
    "header_checksum": "0C",
    "global_checksum": "9F4F",
    "fullName": "Rock'n! Monster!! (Japan) (SGB Enhanced)",
    "coverImage": "/covers/Rock'n! Monster!! (Japan) (SGB Enhanced).png",
    "publisher_cart": "Hori",
    "releaseDate": "1994",
    "releaseMonth": "7",
    "genre": "Puzzle-Game",
    "crc": "630299C1",
    "cartSize": 524288,
    "checksum1000": "DF7D",
    "checksumFull": "338A03D"
}