{
    "title": "ROCKMANWORLD3",
    "platform": "Game Boy",
    "sgb_support": "",
    "publisher": "Capcom",
    "publisher_code": "08",
    "cartridge_type": "ROM+MBC1",
    "cartridge_type_code": "01",
    "rom_size": "256KB",
    "rom_size_code": "03",
    "ram_size": "0KB",
    "ram_size_code": "00",
    "destination": "Japan",
    "version": "00",
    "header_checksum": "15",
    "global_checksum": "AF45",
    "fullName": "Rockman World 3 (Japan)",
    "coverImage": "/covers/Rockman World 3 (Japan).png",
    "publisher_cart": "Capcom",
    "releaseDate": "1992",
    "releaseMonth": "12",
    "genre": "Platform",
    "crc": "E904484F",
    "cartSize": 262144,
    "checksum1000": "67C9",
    "checksumFull": "19EB039"
}