{
    "title": "SUPER MARIOLAND7",
    "platform": "Game Boy",
    "sgb_support": "",
    "publisher": "Unknown Publisher",
    "publisher_code": "18",
    "cartridge_type": "ROM+MBC1",
    "cartridge_type_code": "01",
    "rom_size": "256KB",
    "rom_size_code": "03",
    "ram_size": "0KB",
    "ram_size_code": "00",
    "destination": "",
    "version": "00",
    "header_checksum": "4D",
    "global_checksum": "F736",
    "fullName": "Super Mario World 7 (Taiwan) (Unl)",
    "coverImage": null,
    "publisher_cart": "Hudson Soft Japan",
    "releaseDate": "Unknown Date",
    "releaseMonth": "Unknown Month",
    "genre": "Unknown Genre",
    "crc": "AAD1226E",
    "cartSize": 262144,
    "checksum1000": "4F75",
    "checksumFull": "136F84B"
}