{
    "title": "SWEET ANGE AUBJ",
    "platform": "Game Boy Color",
    "sgb_support": "yes",
    "publisher": "Koei",
    "publisher_code": "C8",
    "cartridge_type": "ROM+MBC5+RAM+BATT",
    "cartridge_type_code": "1B",
    "rom_size": "1MB",
    "rom_size_code": "05",
    "ram_size": "8KB",
    "ram_size_code": "02",
    "destination": "Japan",
    "version": "00",
    "header_checksum": "AF",
    "global_checksum": "2C22",
    "fullName": "Sweet Ange (Japan) (SGB Enhanced) (GB Compatible)",
    "coverImage": "/covers/Sweet Ange (Japan) (SGB Enhanced) (GB Compatible).png",
    "publisher_cart": "Koei",
    "releaseDate": "1999",
    "releaseMonth": "12",
    "genre": "Strategy",
    "crc": "4BE9B159",
    "cartSize": 1048576,
    "checksum1000": "219CE",
    "checksumFull": "8492C70"
}