{
    "title": "TUROK 2",
    "platform": "Game Boy Color",
    "sgb_support": "",
    "publisher": "Acclaim",
    "publisher_code": "B0",
    "cartridge_type": "ROM+MBC5",
    "cartridge_type_code": "19",
    "rom_size": "1MB",
    "rom_size_code": "05",
    "ram_size": "0KB",
    "ram_size_code": "00",
    "destination": "Japan",
    "version": "00",
    "header_checksum": "BD",
    "global_checksum": "FDBD",
    "fullName": "Turok 2 - Jikku Senshi (Japan) (GB Compatible)",
    "coverImage": "/covers/Turok 2 - Jikku Senshi (Japan) (GB Compatible).png",
    "publisher_cart": "Acclaim Japan",
    "releaseDate": "1999",
    "releaseMonth": "9",
    "genre": "Action",
    "crc": "F095B446",
    "cartSize": 1048576,
    "checksum1000": "7CE7",
    "checksumFull": "1CAFF77"
}