{
    "title": "WINTER GOLD",
    "platform": "Game Boy",
    "sgb_support": "",
    "publisher": "U.S. Gold",
    "publisher_code": "4F",
    "cartridge_type": "ROM+MBC1",
    "cartridge_type_code": "01",
    "rom_size": "128KB",
    "rom_size_code": "02",
    "ram_size": "0KB",
    "ram_size_code": "00",
    "destination": "",
    "version": "00",
    "header_checksum": "75",
    "global_checksum": "266F",
    "fullName": "Winter Gold (Europe)",
    "coverImage": "/covers/Winter Gold (Europe).png",
    "publisher_cart": "Eidos/U.S. Gold",
    "releaseDate": "Unknown Date",
    "releaseMonth": "Unknown Month",
    "genre": "Sports",
    "crc": "3C4CD245",
    "cartSize": 131072,
    "checksum1000": "362D",
    "checksumFull": "D12704"
}