{
    "title": "WORLD CUP 98",
    "platform": "Super Game Boy",
    "sgb_support": "yes",
    "publisher": "THQ",
    "publisher_code": "78",
    "cartridge_type": "ROM+MBC1",
    "cartridge_type_code": "01",
    "rom_size": "512KB",
    "rom_size_code": "04",
    "ram_size": "0KB",
    "ram_size_code": "00",
    "destination": "",
    "version": "00",
    "header_checksum": "1B",
    "global_checksum": "90A4",
    "fullName": "World Cup 98 (USA, Europe) (SGB Enhanced)",
    "coverImage": "/covers/World Cup 98 (USA, Europe) (SGB Enhanced).png",
    "publisher_cart": "THQ",
    "releaseDate": "Unknown Date",
    "releaseMonth": "Unknown Month",
    "genre": "Sports",
    "crc": "6A3272B1",
    "cartSize": 524288,
    "checksum1000": "126D0",
    "checksumFull": "47991D8"
}